Workbook

Sheet Start
A1: Topic | B1: Instruction
A2: BLANK TEMPLATE | B2: Copy this file outside the repository before entering real prospect, client, payment or time records. Never commit the populated copy.
A3: Purpose | B3: One 30-day acquisition batch and delivery/support for its first two paid Capability Website pilots. No research or sales have been performed.
A4: Order | B4: Set dates in Settings; record discovery in Leads; standardized offers in Offers; actual effort in Time; receipts/refunds/costs in Cash; first two projects in Pilots; inspect Review.
A5: Reserved IDs | B5: L01–L30, O01–O08 and P1/P2 are empty slots, not actual prospects or projects. One unique Lead ID per business.
A6: Input convention | B6: Use Yes, No or Unknown for evidence fields. Blank means not recorded. Use real numbers for INR and decimal hours. Dates should be consistent, preferably YYYY-MM-DD.
A7: Limits | B7: 30 lead slots; eight distinct offer slots; two pilot slots. Time and Cash calculations include rows 2–501 only. Extend every affected formula before exceeding these ranges.
A8: Settings | B8: Review dates are manual: ten working days for A, 30 calendar days for B. Account for local holidays. Set review-complete flags to Yes when you actually review the evidence.
A9: Leads | B9: Record owner-level substantive conversations, a specific information problem, a concrete trigger within 90 days and feasible approved inputs. No problem or urgency is useful evidence too.
A10: Offers | B10: Eligibility requires need, authority, timing and feasible inputs—not prior willingness to pay. Actual fee, unchanged scope, obligations explained and labelled example shown are required for the standardized test.
A11: Formula cells | B11: Do not overwrite Offers J:L, Pilots I:R or Review B. Settings B4 is also calculated. Cells are not locked; there are no enforced dropdowns.
A12: Time | B12: Columns: date; stage A/B/Delivery; Lead ID or POOL; category; decimal hours; private reference. Use exact category Prospecting for research/initial contact work.
... A22: Companion files | B22: owner-interview-guide.md explains the tests. capability-website-scope.md is the only buyer-facing asset. A labelled demonstration concept is not included in this kit.

Sheet Settings
A1: Parameter | B1: Value | C1: Meaning
A2: Pilot service fee INR | B2: 18000 | C2: Service fee before any applicable taxes; chosen test price, not a measured market rate.
A3: Deposit fraction | B3: 0.5 | C3: 50% of service fee.
A4: Required deposit INR | B4: =B2*B3 | C4: Net fee received, excluding taxes/pass-throughs.
A5: Target shop limit | B5: 30 | C5: Up to 30 named shops for access test.
A6: Owner conversation target | B6: 6 | C6: Substantive conversations with distinct owners/approvers.
A7: Problem plus trigger target | B7: 3 | C7: Must have both a concrete problem and an active trigger.
A8: Eligible offer target | B8: 8 | C8: Distinct businesses shown unchanged scope and labelled example.
A9: Qualifying deposit target | B9: 2 | C9: Net receipts of at least required deposit; no scope/price concessions.
A10: A prospecting hour cap | B10: 10 | C10: Research/initial-contact effort logged as stage A, category Prospecting.
A11: Pilot all-in hour cap | B11: 20 | C11: Includes direct work, shared/unsuccessful sales and remaining support reserve.
A12: Contribution floor INR/hour | B12: 800 | C12: Cash contribution before founder pay and overhead; provisional guardrail.
A13: Illustrative founder allowance INR/hour | B13: 500 | C13: For planning only; not an actual wage expense or net profit calculation.
A14: A review complete? | C14: Enter Yes only when the access-test review has taken place.
A15: B review complete? | C15: Enter Yes only when the 30-day sales review has taken place.
A16: Batch start date | C16: Set before prospecting; no experiment is started by creating this file.
A17: A review date | C17: Ten working days from the chosen start; account for local holidays manually.
A18: B review date | C18: 30 calendar days from the chosen start.

Sheet Leads
A1: Lead ID | B1: Business name (private) | C1: Locality | D1: Source / private reference | E1: First contact date | F1: Owner conversation date | G1: Owner / approver spoke? | H1: Substantive conversation? | I1: Concrete information problem? | J1: Specific problem evidence | K1: Active trigger within 90 days? | L1: Trigger and approximate date | M1: Feasible approved inputs? | N1: Contact / follow-up permission | O1: Next action and date | P1: No-fit / refusal reason
A2: L01
A3: L02
A4: L03
A5: L04
A6: L05
A7: L06
A8: L07
A9: L08
A10: L09
A11: L10
A12: L11
A13: L12
... A31: L30

Sheet Offers
A1: Offer ID | B1: Lead ID | C1: Date presented | D1: Eligible with documented need/authority/timing/inputs? | E1: Actual service fee INR | F1: Same scope / no concessions? | G1: Tax and third-party obligations explained? | H1: Labelled example shown? | I1: Objection / next action / private reference | J1: Net fee received INR (formula) | K1: Counts as standardized offer (formula) | L1: Qualifying deposit 1/0 (formula)
A2: O01 | J2: =IF(B2="","",SUMIFS(Cash!$D$2:$D$501,Cash!$B$2:$B$501,B2,Cash!$C$2:$C$501,"Fee received")-SUMIFS(Cash!$D$2:$D$501,Cash!$B$2:$B$501,B2,Cash!$C$2:$C$501,"Fee refund")) | K2: =IF(B2="","",IF(AND(COUNTIF($B$2:$B$9,B2)=1,COUNTIFS(Leads!$A$2:$A$31,B2,Leads!$B$2:$B$31,"<>")=1,C2<>"",D2="Yes",E2=Settings!$B$2,F2="Yes",G2="Yes",H2="Yes"),1,0)) | L2: =IF(B2="","",IF(AND(K2=1,J2>=Settings!$B$4),1,0))
A3: O02 | J3: =IF(B3="","",SUMIFS(Cash!$D$2:$D$501,Cash!$B$2:$B$501,B3,Cash!$C$2:$C$501,"Fee received")-SUMIFS(Cash!$D$2:$D$501,Cash!$B$2:$B$501,B3,Cash!$C$2:$C$501,"Fee refund")) | K3: =IF(B3="","",IF(AND(COUNTIF($B$2:$B$9,B3)=1,COUNTIFS(Leads!$A$2:$A$31,B3,Leads!$B$2:$B$31,"<>")=1,C3<>"",D3="Yes",E3=Settings!$B$2,F3="Yes",G3="Yes",H3="Yes"),1,0)) | L3: =IF(B3="","",IF(AND(K3=1,J3>=Settings!$B$4),1,0))
A4: O03 | J4: =IF(B4="","",SUMIFS(Cash!$D$2:$D$501,Cash!$B$2:$B$501,B4,Cash!$C$2:$C$501,"Fee received")-SUMIFS(Cash!$D$2:$D$501,Cash!$B$2:$B$501,B4,Cash!$C$2:$C$501,"Fee refund")) | K4: =IF(B4="","",IF(AND(COUNTIF($B$2:$B$9,B4)=1,COUNTIFS(Leads!$A$2:$A$31,B4,Leads!$B$2:$B$31,"<>")=1,C4<>"",D4="Yes",E4=Settings!$B$2,F4="Yes",G4="Yes",H4="Yes"),1,0)) | L4: =IF(B4="","",IF(AND(K4=1,J4>=Settings!$B$4),1,0))
A5: O04 | J5: =IF(B5="","",SUMIFS(Cash!$D$2:$D$501,Cash!$B$2:$B$501,B5,Cash!$C$2:$C$501,"Fee received")-SUMIFS(Cash!$D$2:$D$501,Cash!$B$2:$B$501,B5,Cash!$C$2:$C$501,"Fee refund")) | K5: =IF(B5="","",IF(AND(COUNTIF($B$2:$B$9,B5)=1,COUNTIFS(Leads!$A$2:$A$31,B5,Leads!$B$2:$B$31,"<>")=1,C5<>"",D5="Yes",E5=Settings!$B$2,F5="Yes",G5="Yes",H5="Yes"),1,0)) | L5: =IF(B5="","",IF(AND(K5=1,J5>=Settings!$B$4),1,0))
A6: O05 | J6: =IF(B6="","",SUMIFS(Cash!$D$2:$D$501,Cash!$B$2:$B$501,B6,Cash!$C$2:$C$501,"Fee received")-SUMIFS(Cash!$D$2:$D$501,Cash!$B$2:$B$501,B6,Cash!$C$2:$C$501,"Fee refund")) | K6: =IF(B6="","",IF(AND(COUNTIF($B$2:$B$9,B6)=1,COUNTIFS(Leads!$A$2:$A$31,B6,Leads!$B$2:$B$31,"<>")=1,C6<>"",D6="Yes",E6=Settings!$B$2,F6="Yes",G6="Yes",H6="Yes"),1,0)) | L6: =IF(B6="","",IF(AND(K6=1,J6>=Settings!$B$4),1,0))
A7: O06 | J7: =IF(B7="","",SUMIFS(Cash!$D$2:$D$501,Cash!$B$2:$B$501,B7,Cash!$C$2:$C$501,"Fee received")-SUMIFS(Cash!$D$2:$D$501,Cash!$B$2:$B$501,B7,Cash!$C$2:$C$501,"Fee refund")) | K7: =IF(B7="","",IF(AND(COUNTIF($B$2:$B$9,B7)=1,COUNTIFS(Leads!$A$2:$A$31,B7,Leads!$B$2:$B$31,"<>")=1,C7<>"",D7="Yes",E7=Settings!$B$2,F7="Yes",G7="Yes",H7="Yes"),1,0)) | L7: =IF(B7="","",IF(AND(K7=1,J7>=Settings!$B$4),1,0))
A8: O07 | J8: =IF(B8="","",SUMIFS(Cash!$D$2:$D$501,Cash!$B$2:$B$501,B8,Cash!$C$2:$C$501,"Fee received")-SUMIFS(Cash!$D$2:$D$501,Cash!$B$2:$B$501,B8,Cash!$C$2:$C$501,"Fee refund")) | K8: =IF(B8="","",IF(AND(COUNTIF($B$2:$B$9,B8)=1,COUNTIFS(Leads!$A$2:$A$31,B8,Leads!$B$2:$B$31,"<>")=1,C8<>"",D8="Yes",E8=Settings!$B$2,F8="Yes",G8="Yes",H8="Yes"),1,0)) | L8: =IF(B8="","",IF(AND(K8=1,J8>=Settings!$B$4),1,0))
A9: O08 | J9: =IF(B9="","",SUMIFS(Cash!$D$2:$D$501,Cash!$B$2:$B$501,B9,Cash!$C$2:$C$501,"Fee received")-SUMIFS(Cash!$D$2:$D$501,Cash!$B$2:$B$501,B9,Cash!$C$2:$C$501,"Fee refund")) | K9: =IF(B9="","",IF(AND(COUNTIF($B$2:$B$9,B9)=1,COUNTIFS(Leads!$A$2:$A$31,B9,Leads!$B$2:$B$31,"<>")=1,C9<>"",D9="Yes",E9=Settings!$B$2,F9="Yes",G9="Yes",H9="Yes"),1,0)) | L9: =IF(B9="","",IF(AND(K9=1,J9>=Settings!$B$4),1,0))

Sheet Time
A1: Date | B1: Stage: A / B / Delivery | C1: Lead ID or POOL | D1: Category | E1: Hours (decimal) | F1: Private reference / note

Sheet Cash
A1: Date | B1: Lead ID or POOL | C1: Type: Fee received / Fee refund / External cost | D1: Amount INR (positive) | E1: Private receipt / evidence reference | F1: Note (service-fee portion only)

Sheet Pilots
A1: Pilot ID | B1: Lead ID | C1: Agreed service fee INR | D1: Client accepted? | E1: Enquiry receipt and handover checked? | F1: 30-day defect window reconciled? | G1: All batch records complete? | H1: Remaining support reserve hours | I1: Direct logged hours (formula) | J1: Allocated shared hours (formula) | K1: All-in hours (formula) | L1: Net service fee collected INR (formula) | M1: Direct external costs INR (formula) | N1: Allocated shared costs INR (formula) | O1: Cash contribution before labour/overhead INR (formula) | P1: Cash contribution INR/hour (formula) | Q1: After illustrative labour, before overhead/tax INR (formula) | R1: Economic status (formula)
A2: P1 | I2: =IF(B2="","",SUMIF(Time!$C$2:$C$501,B2,Time!$E$2:$E$501)) | J2: =IF(B2="","",(SUM(Time!$E$2:$E$501)-SUM($I$2:$I$3))/COUNTIF($B$2:$B$3,"?*")) | K2: =IF(OR(B2="",NOT(ISNUMBER(H2))),"",I2+J2+H2) | L2: =IF(B2="","",SUMIFS(Cash!$D$2:$D$501,Cash!$B$2:$B$501,B2,Cash!$C$2:$C$501,"Fee received")-SUMIFS(Cash!$D$2:$D$501,Cash!$B$2:$B$501,B2,Cash!$C$2:$C$501,"Fee refund")) | M2: =IF(B2="","",SUMIFS(Cash!$D$2:$D$501,Cash!$B$2:$B$501,B2,Cash!$C$2:$C$501,"External cost")) | N2: =IF(B2="","",(SUMIF(Cash!$C$2:$C$501,"External cost",Cash!$D$2:$D$501)-SUM($M$2:$M$3))/COUNTIF($B$2:$B$3,"?*")) | O2: =IF(B2="","",L2-M2-N2) | P2: =IF(OR(B2="",K2="",K2<=0),"",O2/K2) | Q2: =IF(OR(B2="",K2=""),"",O2-K2*Settings!$B$13) | R2: =IF(B2="","Not started",IF(OR(COUNTIF($B$2:$B$3,B2)>1,COUNTIF(Leads!$A$2:$A$31,B2)<>1,C2<>Settings!$B$2,COUNTIF(Time!$E$2:$E$501,"<0")>0,COUNTIF(Cash!$D$2:$D$501,"<0")>0),"Check inputs",IF(OR(D2<>"Yes",E2<>"Yes",F2<>"Yes",G2<>"Yes",NOT(ISNUMBER(H2)),H2<>0),"Provisional",IF(L2<C2,"Await balance",IF(OR(K2<=0,P2=""),"Check hours",IF(AND(K2<=Settings!$B$11,P2>=Settings!$B$12),"Meets guardrail","Rework scope/cost"))))))
A3: P2 | I3: =IF(B3="","",SUMIF(Time!$C$2:$C$501,B3,Time!$E$2:$E$501)) | J3: =IF(B3="","",(SUM(Time!$E$2:$E$501)-SUM($I$2:$I$3))/COUNTIF($B$2:$B$3,"?*")) | K3: =IF(OR(B3="",NOT(ISNUMBER(H3))),"",I3+J3+H3) | L3: =IF(B3="","",SUMIFS(Cash!$D$2:$D$501,Cash!$B$2:$B$501,B3,Cash!$C$2:$C$501,"Fee received")-SUMIFS(Cash!$D$2:$D$501,Cash!$B$2:$B$501,B3,Cash!$C$2:$C$501,"Fee refund")) | M3: =IF(B3="","",SUMIFS(Cash!$D$2:$D$501,Cash!$B$2:$B$501,B3,Cash!$C$2:$C$501,"External cost")) | N3: =IF(B3="","",(SUMIF(Cash!$C$2:$C$501,"External cost",Cash!$D$2:$D$501)-SUM($M$2:$M$3))/COUNTIF($B$2:$B$3,"?*")) | O3: =IF(B3="","",L3-M3-N3) | P3: =IF(OR(B3="",K3="",K3<=0),"",O3/K3) | Q3: =IF(OR(B3="",K3=""),"",O3-K3*Settings!$B$13) | R3: =IF(B3="","Not started",IF(OR(COUNTIF($B$2:$B$3,B3)>1,COUNTIF(Leads!$A$2:$A$31,B3)<>1,C3<>Settings!$B$2,COUNTIF(Time!$E$2:$E$501,"<0")>0,COUNTIF(Cash!$D$2:$D$501,"<0")>0),"Check inputs",IF(OR(D3<>"Yes",E3<>"Yes",F3<>"Yes",G3<>"Yes",NOT(ISNUMBER(H3)),H3<>0),"Provisional",IF(L3<C3,"Await balance",IF(OR(K3<=0,P3=""),"Check hours",IF(AND(K3<=Settings!$B$11,P3>=Settings!$B$12),"Meets guardrail","Rework scope/cost"))))))

Sheet Review
A1: Metric | B1: Value (formula) | C1: Interpretation
A2: Named businesses | B2: =COUNTIF(Leads!$B$2:$B$31,"<>") | C2: Reserved Lead IDs alone are not businesses.
A3: Businesses contacted | B3: =COUNTIFS(Leads!$B$2:$B$31,"<>",Leads!$E$2:$E$31,"<>") | C3: Count distinct businesses, not messages.
A4: Substantive owner conversations | B4: =COUNTIFS(Leads!$B$2:$B$31,"<>",Leads!$F$2:$F$31,"<>",Leads!$G$2:$G$31,"Yes",Leads!$H$2:$H$31,"Yes") | C4: Target 6; retain no-need responses.
A5: Owner conversations with problem AND trigger | B5: =COUNTIFS(Leads!$B$2:$B$31,"<>",Leads!$F$2:$F$31,"<>",Leads!$G$2:$G$31,"Yes",Leads!$H$2:$H$31,"Yes",Leads!$I$2:$I$31,"Yes",Leads!$J$2:$J$31,"<>",Leads!$K$2:$K$31,"Yes",Leads!$L$2:$L$31,"<>") | C5: Target 3; written incident and trigger evidence required.
A6: A prospecting hours | B6: =SUMIFS(Time!$E$2:$E$501,Time!$B$2:$B$501,"A",Time!$D$2:$D$501,"Prospecting") | C6: Cap 10; stage B later work is separate.
A7: Standardized eligible offers | B7: =SUM(Offers!$K$2:$K$9) | C7: Target 8. Inspect K=0 rows; duplicates, missing example, changed scope or price do not count.
A8: Qualifying net deposits | B8: =SUM(Offers!$L$2:$L$9) | C8: Target 2. Refunds reduce net receipts; promises are not payments.
A9: Shared / unsuccessful-selling pool hours | B9: =SUM(Time!$E$2:$E$501)-SUM(Pilots!$I$2:$I$3) | C9: Allocated equally across populated pilot slots; all batch work must be captured.
A10: Shared / unsuccessful-selling pool costs INR | B10: =SUMIF(Cash!$C$2:$C$501,"External cost",Cash!$D$2:$D$501)-SUM(Pilots!$M$2:$M$3) | C10: Includes non-winning leads' costs and POOL; never allocate twice.
A11: Pilots meeting guardrails | B11: =COUNTIF(Pilots!$R$2:$R$3,"Meets guardrail") | C11: Both required. Check completeness and support reconciliation.
A12: A access/urgency indicator | B12: =IF(B6>Settings!$B$10,"Review effort cap",IF(AND(B4>=Settings!$B$6,B5>=Settings!$B$7),"Signal reached",IF(Settings!$B$14="Yes","Stop/reassess access or need",IF(B3=0,"Not started","In progress")))) | C12: At review, distinguish inaccessible owners from absent urgency. Clinics are a sequential fallback, not a parallel campaign.
A13: B paid-demand indicator | B13: =IF(AND(B7>=Settings!$B$8,B8>=Settings!$B$9),"Paid signal reached",IF(Settings!$B$15="Yes",IF(B7<Settings!$B$8,"Unresolved: too few offers","Insufficient paid signal"),IF(B7=0,"Not started","In progress"))) | C13: No automatic discount or scaling. Investigate refusal reasons and missing sample.
A14: C delivery indicator | B14: =IF(COUNTIF(Pilots!$B$2:$B$3,"?*")=0,"Not started",IF(B11=2,"Meets pilot guardrails","Provisional / inspect Pilots")) | C14: Positive status requires owner-confirmed complete records; not a verified profit claim or proof of client sales outcomes.
A15: Negative-entry warning | B15: =IF(COUNTIF(Time!$E$2:$E$501,"<0")+COUNTIF(Cash!$D$2:$D$501,"<0")>0,"Fix negative input; use refund type","No negative numeric entries") | C15: This checks negatives only, not full data quality. Unknown IDs/types, omissions and duplicate events require manual review.
A16: Decision boundary | B16: Manual review required | C16: Continue the niche only with access, urgency and paid demand. Increase acquisition only after delivery economics. Reconcile support before relying on C.
